run.py
infinity_mouse-0.2.4.dist-info/licenses/LICENSE
infinity_mouse-0.2.4.dist-info/METADATA
infinity_mouse-0.2.4.dist-info/WHEEL
infinity_mouse-0.2.4.dist-info/entry_points.txt
infinity_mouse-0.2.4.dist-info/top_level.txt
infinity_mouse-0.2.4.dist-info/RECORD
