Metadata-Version: 2.4
Name: infinity-mouse
Version: 0.2.4
Summary: Mouse infinity movement after timeout.
Home-page: https://github.com/mqxym/infinity-mouse
Author: mqxym
Author-email: maxim@omg.lol
Platform: MacOS
Classifier: License :: OSI Approved :: MIT License
Requires-Python: >=3.9
License-File: LICENSE
Requires-Dist: pyobjc-framework-Quartz
Requires-Dist: pyautogui
Requires-Dist: screeninfo
Dynamic: author
Dynamic: author-email
Dynamic: classifier
Dynamic: description
Dynamic: description-content-type
Dynamic: home-page
Dynamic: license-file
Dynamic: platform
Dynamic: requires-dist
Dynamic: requires-python
Dynamic: summary
